{
  "type": "Feature",
  "properties": {
    "gn:country":"KI",
    "gn:fcode":"ADM2",
    "gn:pop":301,
    "iso:country":"KI",
    "name:unk_x_variant":[
        "Ocean Island"
    ],
    "qs:name":"Banaba",
    "qs:photos_9r":0,
    "qs:photos_sr":0,
    "qs:pop_sr":"2",
    "wof:name":"Banaba",
    "wof:placetype":"county",
    "wof:population":301
},
  "geometry": {"coordinates":[169.53800000000001,-0.855],"type":"Point"}
}