{
  "type": "Feature",
  "properties": {
    "gn:country":"KI",
    "gn:fcode":"ADM2",
    "gn:population":301,
    "iso:country":"KI",
    "label:eng_x_preferred_longname":[
        "Banaba Council"
    ],
    "label:eng_x_preferred_placetype":[
        "council"
    ],
    "name:ben_x_preferred":[
        "\u09ac\u09be\u09a8\u09be\u09ac\u09be"
    ],
    "name:eng_x_preferred":[
        "Banaba"
    ],
    "name:fra_x_preferred":[
        "Banaba"
    ],
    "name:hin_x_preferred":[
        "\u092c\u0928\u093e\u092c\u093e"
    ],
    "name:hun_x_preferred":[
        "Banaba"
    ],
    "name:und_x_variant":[
        "Ocean Island"
    ],
    "name:urd_x_preferred":[
        "\u0628\u0627\u0646\u0627\u0628\u0627"
    ],
    "qs:name":"Banaba",
    "qs:photos_9r":0,
    "qs:photos_sr":0,
    "qs:pop_sr":"2",
    "wof:name":"Banaba",
    "wof:placetype":"county",
    "wof:population":301
},
  "geometry": {"coordinates":[169.53800000000001,-0.855],"type":"Point"}
}