{
  "type": "Feature",
  "properties": {
    "gn:country":"KI",
    "gn:fcode":"ADM2",
    "gn:population":2539,
    "iso:country":"KI",
    "name:bel_x_preferred":[
        "\u0410\u0442\u043e\u043b \u0422\u0430\u0431\u0443\u0430\u044d\u0440\u0430\u043d"
    ],
    "name:ces_x_preferred":[
        "Tabuaeran"
    ],
    "name:deu_x_preferred":[
        "Tabuaeran"
    ],
    "name:ell_x_preferred":[
        "\u03a4\u03b1\u03bc\u03c0\u03bf\u03c5\u03b1\u03b5\u03c1\u03ac\u03bd"
    ],
    "name:eng_x_preferred":[
        "Tabuaeran"
    ],
    "name:est_x_preferred":[
        "Tabuaeran"
    ],
    "name:fas_x_preferred":[
        "\u062a\u0627\u0628\u0648\u0622\u0626\u0631\u0627\u0646"
    ],
    "name:fin_x_preferred":[
        "Fanninginsaari"
    ],
    "name:fra_x_preferred":[
        "Tabuaeran"
    ],
    "name:glg_x_preferred":[
        "Atol Tabuaeran"
    ],
    "name:heb_x_preferred":[
        "\u05d8\u05d1\u05d5\u05d0\u05d0\u05e8\u05d0\u05df"
    ],
    "name:hrv_x_preferred":[
        "Tabuaeran"
    ],
    "name:ind_x_preferred":[
        "Tabuaeran"
    ],
    "name:ita_x_preferred":[
        "Tabuaeran"
    ],
    "name:jpn_x_preferred":[
        "\u30bf\u30d6\u30a2\u30a8\u30e9\u30f3\u5cf6"
    ],
    "name:kor_x_preferred":[
        "\ud0c0\ubd80\uc544\uc5d0\ub780 \uc12c"
    ],
    "name:kor_x_variant":[
        "\ud0c0\ubd80\uc544\uc5d0\ub780\uc12c"
    ],
    "name:lit_x_preferred":[
        "Tabuaeranas"
    ],
    "name:mal_x_preferred":[
        "\u0d1f\u0d3e\u0d2c\u0d40\u0d31\u0d7b"
    ],
    "name:mkd_x_preferred":[
        "\u0422\u0430\u0431\u0443\u0430\u0435\u0440\u0430\u043d"
    ],
    "name:nld_x_preferred":[
        "Tabuaeran"
    ],
    "name:ron_x_preferred":[
        "Tabuaeran"
    ],
    "name:rus_x_preferred":[
        "\u0422\u0430\u0431\u0443\u0430\u044d\u0440\u0430\u043d"
    ],
    "name:spa_x_preferred":[
        "Tabuaeran"
    ],
    "name:swe_x_preferred":[
        "Tabuaeran"
    ],
    "name:tur_x_preferred":[
        "Tabuaeran"
    ],
    "name:ukr_x_preferred":[
        "\u0422\u0430\u0431\u0443\u0430\u0435\u0440\u0430\u043d"
    ],
    "name:zho_x_preferred":[
        "\u5854\u5e03\u963f\u57c3\u862d\u74b0\u7901"
    ],
    "qs:name":"Tabuaeran",
    "qs:photos_9r":0,
    "qs:photos_sr":0,
    "qs:pop_sr":"4",
    "wd:wordcount":1093,
    "wof:name":"Tabuaeran",
    "wof:placetype":"county",
    "wof:population":2539
},
  "geometry": {"coordinates":[-159.33332999999999,3.86667],"type":"Point"}
}