{
  "type": "Feature",
  "properties": {
    "gn:country":"KI",
    "gn:fcode":"PPL",
    "gn:pop":148,
    "iso:country":"KI",
    "qs:name":"Tematantongo Village",
    "qs:photos_9r":0,
    "qs:photos_sr":0,
    "qs:pop_sr":"1",
    "wd:wordcount":702,
    "wof:name":"Tematantongo Village",
    "wof:placetype":"locality",
    "wof:population":148
},
  "geometry": {"coordinates":[173.04555999999999,0.99252],"type":"Point"}
}