{
  "type": "Feature",
  "properties": {
    "gn:country":"KI",
    "gn:fcode":"PPL",
    "gn:pop":140,
    "iso:country":"KI",
    "name:unk_x_variant":[
        "OSCAR WW2"
    ],
    "qs:name":"Kariatebike Village",
    "qs:photos_9r":0,
    "qs:photos_sr":0,
    "qs:pop_sr":"1",
    "wd:wordcount":1137,
    "wof:name":"Kariatebike Village",
    "wof:placetype":"locality",
    "wof:population":140
},
  "geometry": {"coordinates":[173.91988000000001,0.40456],"type":"Point"}
}