{
  "type": "Feature",
  "properties": {
    "gn:country":"KI",
    "gn:fcode":"PPL",
    "gn:population":140,
    "iso:country":"KI",
    "name:bul_x_preferred":[
        "\u0410\u0431\u0435\u043c\u0430\u043c\u0430"
    ],
    "name:ceb_x_preferred":[
        "Abemama"
    ],
    "name:ces_x_preferred":[
        "Abemama"
    ],
    "name:deu_x_preferred":[
        "Abemama"
    ],
    "name:ell_x_preferred":[
        "\u0391\u03bc\u03c0\u03b5\u03bc\u03ac\u03bc\u03b1"
    ],
    "name:eng_x_preferred":[
        "Abemama"
    ],
    "name:fao_x_preferred":[
        "Abemama"
    ],
    "name:fas_x_preferred":[
        "\u0622\u0628\u0645\u0627\u0645\u0627"
    ],
    "name:fin_x_preferred":[
        "Abemama"
    ],
    "name:fra_x_preferred":[
        "Abemama"
    ],
    "name:glg_x_preferred":[
        "Atol Abemama"
    ],
    "name:heb_x_preferred":[
        "\u05d0\u05d1\u05de\u05d0\u05de\u05d4"
    ],
    "name:hrv_x_preferred":[
        "Abemama"
    ],
    "name:hye_x_preferred":[
        "\u0531\u0562\u0565\u0574\u0561\u0574\u0561"
    ],
    "name:ita_x_preferred":[
        "Abemama"
    ],
    "name:jpn_x_preferred":[
        "\u30a2\u30d9\u30de\u30de"
    ],
    "name:kat_x_preferred":[
        "\u10d0\u10d1\u10d4\u10db\u10d0\u10db\u10d0"
    ],
    "name:kor_x_preferred":[
        "\uc544\ubca0\ub9c8\ub9c8"
    ],
    "name:lit_x_preferred":[
        "Abemama"
    ],
    "name:mkd_x_preferred":[
        "\u0410\u0431\u0435\u043c\u0430\u043c\u0430"
    ],
    "name:nld_x_preferred":[
        "Abemama"
    ],
    "name:pol_x_preferred":[
        "Abemama"
    ],
    "name:por_x_preferred":[
        "Abemama"
    ],
    "name:rus_x_preferred":[
        "\u0410\u0431\u0435\u043c\u0430\u043c\u0430"
    ],
    "name:spa_x_preferred":[
        "Abemama"
    ],
    "name:swe_x_preferred":[
        "Abemama"
    ],
    "name:tur_x_preferred":[
        "Abemama"
    ],
    "name:ukr_x_preferred":[
        "\u0410\u0431\u0435\u043c\u0430\u043c\u0430"
    ],
    "name:und_x_variant":[
        "OSCAR WW2"
    ],
    "name:zho_x_preferred":[
        "\u963f\u8c9d\u99ac\u99ac\u74b0\u7901"
    ],
    "qs:name":"Kariatebike Village",
    "qs:photos_9r":0,
    "qs:photos_sr":0,
    "qs:pop_sr":"1",
    "wd:wordcount":1137,
    "wof:name":"Kariatebike Village",
    "wof:placetype":"locality",
    "wof:population":140
},
  "geometry": {"coordinates":[173.91988000000001,0.40456],"type":"Point"}
}