{
  "type": "Feature",
  "properties": {
    "gn:country":"KI",
    "gn:fcode":"PPL",
    "gn:pop":203,
    "iso:country":"KI",
    "qs:name":"Bikati Village",
    "qs:photos_9r":0,
    "qs:photos_sr":0,
    "qs:pop_sr":"2",
    "wd:wordcount":2295,
    "wof:name":"Bikati Village",
    "wof:placetype":"locality",
    "wof:population":203
},
  "geometry": {"coordinates":[172.68804,3.26],"type":"Point"}
}