{
  "type": "Feature",
  "properties": {
    "gn:country":"KI",
    "gn:fcode":"PPL",
    "gn:pop":246,
    "iso:country":"KI",
    "name:bul_x_preferred":[
        "\u041c\u0430\u0438\u0430\u043d\u0430"
    ],
    "name:ceb_x_preferred":[
        "Maiana"
    ],
    "name:deu_x_preferred":[
        "Maiana"
    ],
    "name:ell_x_preferred":[
        "\u039c\u03b1\u03ca\u03ac\u03bd\u03b1"
    ],
    "name:eng_x_preferred":[
        "Maiana"
    ],
    "name:epo_x_preferred":[
        "Maiana"
    ],
    "name:fas_x_preferred":[
        "\u0645\u0627\u06cc\u0627\u0646\u0627"
    ],
    "name:fin_x_preferred":[
        "Maiana"
    ],
    "name:fra_x_preferred":[
        "Maiana"
    ],
    "name:glg_x_preferred":[
        "Atol Maiana"
    ],
    "name:heb_x_preferred":[
        "\u05de\u05d0\u05d9\u05d0\u05e0\u05d4"
    ],
    "name:hrv_x_preferred":[
        "Maiana"
    ],
    "name:ita_x_preferred":[
        "Maiana"
    ],
    "name:jpn_x_preferred":[
        "\u30de\u30a4\u30a2\u30ca"
    ],
    "name:kor_x_preferred":[
        "\ub9c8\uc774\uc544\ub098\uc12c"
    ],
    "name:mkd_x_preferred":[
        "\u041c\u0430\u0458\u0430\u043d\u0430"
    ],
    "name:nld_x_preferred":[
        "Maiana"
    ],
    "name:pol_x_preferred":[
        "Maiana"
    ],
    "name:por_x_preferred":[
        "Maiana"
    ],
    "name:rus_x_preferred":[
        "\u041c\u0430\u0438\u0430\u043d\u0430"
    ],
    "name:spa_x_preferred":[
        "Maiana"
    ],
    "name:swe_x_preferred":[
        "Maiana"
    ],
    "name:tur_x_preferred":[
        "Maiana"
    ],
    "name:unk_x_variant":[
        "Tebana"
    ],
    "name:zho_x_preferred":[
        "\u99ac\u4e9e\u7d0d\u74b0\u7901"
    ],
    "qs:name":"Tebanga Village",
    "qs:photos_9r":0,
    "qs:photos_sr":0,
    "qs:pop_sr":"2",
    "wd:wordcount":702,
    "wof:name":"Tebanga Village",
    "wof:placetype":"locality",
    "wof:population":246
},
  "geometry": {"coordinates":[173.93529000000001,0.35739],"type":"Point"}
}