{
  "type": "Feature",
  "properties": {
    "gn:country":"KI",
    "gn:fcode":"PPL",
    "gn:pop":246,
    "iso:country":"KI",
    "name:unk_x_variant":[
        "Tebana"
    ],
    "qs:name":"Tebanga Village",
    "qs:photos_9r":0,
    "qs:photos_sr":0,
    "qs:pop_sr":"2",
    "wd:wordcount":702,
    "wof:name":"Tebanga Village",
    "wof:placetype":"locality",
    "wof:population":246
},
  "geometry": {"coordinates":[173.93529000000001,0.35739],"type":"Point"}
}