{
  "type": "Feature",
  "properties": {
    "gn:country":"KI",
    "gn:fcode":"PPL",
    "gn:pop":71,
    "iso:country":"KI",
    "name:eng_x_preferred":[
        "Marenanuka"
    ],
    "name:nld_x_preferred":[
        "Marenanuka"
    ],
    "name:por_x_preferred":[
        "Marenanuka"
    ],
    "name:unk_x_variant":[
        "Maranenuka Village"
    ],
    "qs:name":"Marenanuka Village",
    "qs:photos_9r":0,
    "qs:photos_sr":0,
    "qs:pop_sr":"1",
    "wd:wordcount":1006,
    "wof:name":"Marenanuka Village",
    "wof:placetype":"locality",
    "wof:population":71
},
  "geometry": {"coordinates":[173.02636999999999,1.48735],"type":"Point"}
}