{
  "type": "Feature",
  "properties": {
    "gn:country":"KI",
    "gn:fcode":"ADM2",
    "gn:population":2169,
    "iso:country":"KI",
    "name:ceb_x_preferred":[
        "Beru"
    ],
    "name:deu_x_preferred":[
        "Beru"
    ],
    "name:fra_x_preferred":[
        "Beru"
    ],
    "name:ind_x_preferred":[
        "Beru"
    ],
    "name:nld_x_preferred":[
        "Beru"
    ],
    "name:rus_x_preferred":[
        "\u0411\u0435\u0440\u0443"
    ],
    "name:swe_x_preferred":[
        "Beru"
    ],
    "name:und_x_variant":[
        "Eliza"
    ],
    "qs:name":"Beru",
    "qs:photos_9r":0,
    "qs:photos_sr":0,
    "qs:pop_sr":"4",
    "wof:name":"Beru",
    "wof:placetype":"county",
    "wof:population":2169
},
  "geometry": {"coordinates":[175.98071999999999,-1.32957],"type":"Point"}
}