{
  "type": "Feature",
  "properties": {
    "gn:country":"KI",
    "gn:fcode":"ADM2",
    "gn:pop":2169,
    "iso:country":"KI",
    "name:unk_x_variant":[
        "Eliza"
    ],
    "qs:name":"Beru",
    "qs:photos_9r":0,
    "qs:photos_sr":0,
    "qs:pop_sr":"4",
    "wof:name":"Beru",
    "wof:placetype":"county",
    "wof:population":2169
},
  "geometry": {"coordinates":[175.98071999999999,-1.32957],"type":"Point"}
}