{
  "type": "Feature",
  "properties": {
    "gn:country":"KI",
    "gn:fcode":"PPL",
    "gn:population":34,
    "iso:country":"KI",
    "qs:name":"Tekaitara Village",
    "qs:photos_9r":0,
    "qs:photos_sr":0,
    "qs:pop_sr":"1",
    "wof:name":"Tekaitara Village",
    "wof:placetype":"locality",
    "wof:population":34
},
  "geometry": {"coordinates":[-160.38723999999999,4.69717],"type":"Point"}
}