{
  "type": "Feature",
  "properties": {
    "gn:country":"KI",
    "gn:fcode":"PPL",
    "gn:pop":414,
    "iso:country":"KI",
    "qs:name":"Nabeina Village",
    "qs:photos_9r":0,
    "qs:photos_sr":0,
    "qs:pop_sr":"2",
    "wd:wordcount":1006,
    "wof:name":"Nabeina Village",
    "wof:placetype":"locality",
    "wof:population":414
},
  "geometry": {"coordinates":[173.07918000000001,1.4358],"type":"Point"}
}