{
  "type": "Feature",
  "properties": {
    "gn:country":"KI",
    "gn:fcode":"PPL",
    "gn:population":668,
    "iso:country":"KI",
    "name:ceb_x_preferred":[
        "Toboiaki Village"
    ],
    "name:eng_x_preferred":[
        "Umantewena"
    ],
    "name:nld_x_preferred":[
        "Umantewena"
    ],
    "name:swe_x_preferred":[
        "Toboiaki Village"
    ],
    "name:und_x_variant":[
        "Umanterwena"
    ],
    "qs:name":"Toboiaki Village",
    "qs:photos_9r":0,
    "qs:photos_sr":0,
    "qs:pop_sr":"2",
    "wof:name":"Toboiaki Village",
    "wof:placetype":"locality",
    "wof:population":668
},
  "geometry": {"coordinates":[174.45421999999999,-0.73842],"type":"Point"}
}