{
  "type": "Feature",
  "properties": {
    "gn:country":"KI",
    "gn:fcode":"PPL",
    "gn:pop":190,
    "iso:country":"KI",
    "qs:name":"Arabata Village",
    "qs:photos_9r":0,
    "qs:photos_sr":0,
    "qs:pop_sr":"1",
    "wd:wordcount":3211,
    "wof:name":"Arabata Village",
    "wof:placetype":"locality",
    "wof:population":190
},
  "geometry": {"coordinates":[-160.39743000000001,4.67951],"type":"Point"}
}