{
  "type": "Feature",
  "properties": {
    "gn:country":"KI",
    "gn:fcode":"PPL",
    "gn:pop":186,
    "iso:country":"KI",
    "name:bul_x_preferred":[
        "\u0410\u0438\u0430\u043a\u0438"
    ],
    "name:dut_x_preferred":[
        "Aiaki"
    ],
    "name:eng_x_preferred":[
        "Aiaki"
    ],
    "name:fre_x_preferred":[
        "Aiaki"
    ],
    "name:ger_x_preferred":[
        "Ijaki"
    ],
    "name:pol_x_preferred":[
        "Aiaki"
    ],
    "name:por_x_preferred":[
        "Ijaki"
    ],
    "name:swe_x_preferred":[
        "Aiaki"
    ],
    "name:unk_x_variant":[
        "Ijaki"
    ],
    "qs:name":"Aiaki",
    "qs:photos_9r":0,
    "qs:photos_sr":0,
    "qs:pop_sr":"1",
    "wof:name":"Aiaki",
    "wof:placetype":"locality",
    "wof:population":186
},
  "geometry": {"coordinates":[175.61507,-1.89417],"type":"Point"}
}