{
  "type": "Feature",
  "properties": {
    "gn:country":"KI",
    "gn:fcode":"PPL",
    "gn:pop":106,
    "iso:country":"KI",
    "qs:name":"Kauamwmwe Village",
    "qs:photos_9r":0,
    "qs:photos_sr":0,
    "qs:pop_sr":"1",
    "wof:name":"Kauamwmwe Village",
    "wof:placetype":"locality",
    "wof:population":106
},
  "geometry": {"coordinates":[-160.37120999999999,4.69053],"type":"Point"}
}