{
  "type": "Feature",
  "properties": {
    "gn:country":"KI",
    "gn:fcode":"PPL",
    "gn:pop":204,
    "iso:country":"KI",
    "name:deu_x_preferred":[
        "Kabuna"
    ],
    "name:est_x_preferred":[
        "Kabuna"
    ],
    "name:fra_x_preferred":[
        "Kabuna"
    ],
    "name:hye_x_preferred":[
        "\u053f\u0561\u0562\u0578\u0582\u0576\u0561"
    ],
    "name:pol_x_preferred":[
        "Kabuna"
    ],
    "name:spa_x_preferred":[
        "Kabuna"
    ],
    "name:vol_x_preferred":[
        "Kabuna"
    ],
    "qs:name":"Kabuna Village",
    "qs:photos_9r":0,
    "qs:photos_sr":0,
    "qs:pop_sr":"2",
    "wof:name":"Kabuna Village",
    "wof:placetype":"locality",
    "wof:population":204
},
  "geometry": {"coordinates":[174.79830999999999,-1.28832],"type":"Point"}
}