{
  "type": "Feature",
  "properties": {
    "gn:country":"KI",
    "gn:fcode":"PPL",
    "gn:pop":204,
    "iso:country":"KI",
    "qs:name":"Kabuna Village",
    "qs:photos_9r":0,
    "qs:photos_sr":0,
    "qs:pop_sr":"2",
    "wof:name":"Kabuna Village",
    "wof:placetype":"locality",
    "wof:population":204
},
  "geometry": {"coordinates":[174.79830999999999,-1.28832],"type":"Point"}
}