{
  "type": "Feature",
  "properties": {
    "gn:gn_country":"KI",
    "gn:gn_fcode":"PPL",
    "gn:gn_pop":97,
    "gn:population":97,
    "iso:country":"KI",
    "name:eng_x_preferred":[
        "Tabukiniberu"
    ],
    "name:nld_x_preferred":[
        "Tabukiniberu"
    ],
    "name:pol_x_preferred":[
        "Tabukiniberu"
    ],
    "name:unk_x_variant":[
        "Tabukinberu"
    ],
    "qs_pg:aaroncc":"KI",
    "qs_pg:gn_country":"KI",
    "qs_pg:gn_fcode":"PPL",
    "qs_pg:gn_pop":97,
    "qs_pg:name":"Tabukiniberu Village",
    "qs_pg:photos_9r":0,
    "qs_pg:photos_sr":0,
    "qs_pg:pop_sr":3,
    "qs_pg:qs_pg_placetype":"locality",
    "wof:name":"Tabukiniberu Village",
    "wof:placetype":"locality",
    "wof:population":97
},
  "geometry": {"coordinates":[175.98448999999999,-1.33781],"type":"Point"}
}