{
  "type": "Feature",
  "properties": {
    "gn:country":"KI",
    "gn:fcode":"PPL",
    "gn:pop":304,
    "iso:country":"KI",
    "qs:name":"Teuabu Village",
    "qs:photos_9r":0,
    "qs:photos_sr":0,
    "qs:pop_sr":"2",
    "wd:wordcount":84,
    "wof:name":"Teuabu Village",
    "wof:placetype":"locality",
    "wof:population":304
},
  "geometry": {"coordinates":[174.35091,-0.58113],"type":"Point"}
}