{
  "type": "Feature",
  "properties": {
    "gn:country":"KI",
    "gn:fcode":"PPL",
    "gn:pop":390,
    "iso:country":"KI",
    "qs:name":"Antebuka Village",
    "qs:photos_9r":0,
    "qs:photos_sr":0,
    "qs:pop_sr":"2",
    "wd:wordcount":1710,
    "wof:name":"Antebuka Village",
    "wof:placetype":"locality",
    "wof:population":390
},
  "geometry": {"coordinates":[173.02698000000001,1.34009],"type":"Point"}
}