{
  "type": "Feature",
  "properties": {
    "gn:country":"KI",
    "gn:fcode":"PPL",
    "gn:population":551,
    "iso:country":"KI",
    "name:ceb_x_preferred":[
        "Makin Island"
    ],
    "name:dan_x_preferred":[
        "Makin"
    ],
    "name:deu_x_preferred":[
        "Makin"
    ],
    "name:ell_x_preferred":[
        "\u039c\u03b1\u03ba\u03af\u03bd \u039d\u03ae\u03c3\u03bf\u03c2"
    ],
    "name:eng_x_preferred":[
        "Makin"
    ],
    "name:fas_x_preferred":[
        "\u0645\u0627\u06a9\u06cc\u0646"
    ],
    "name:fin_x_preferred":[
        "Makin"
    ],
    "name:fra_x_preferred":[
        "Makin"
    ],
    "name:hrv_x_preferred":[
        "Makin"
    ],
    "name:ita_x_preferred":[
        "Isole Makin"
    ],
    "name:jpn_x_preferred":[
        "\u30de\u30ad\u30f3\u5cf6"
    ],
    "name:kor_x_preferred":[
        "\ub9c8\ud0a8 \uc12c"
    ],
    "name:lit_x_preferred":[
        "Makinas"
    ],
    "name:mkd_x_preferred":[
        "\u041c\u0430\u043a\u0438\u043d\u0441\u043a\u0438 \u041e\u0441\u0442\u0440\u043e\u0432\u0438"
    ],
    "name:nld_x_preferred":[
        "Makin"
    ],
    "name:pol_x_preferred":[
        "Makin"
    ],
    "name:por_x_preferred":[
        "Makin"
    ],
    "name:rus_x_preferred":[
        "\u041c\u0430\u043a\u0438\u043d"
    ],
    "name:slv_x_preferred":[
        "Makin"
    ],
    "name:spa_x_preferred":[
        "Makin"
    ],
    "name:swe_x_preferred":[
        "Makin"
    ],
    "name:tur_x_preferred":[
        "Makin Adas\u0131"
    ],
    "name:vie_x_preferred":[
        "Makin"
    ],
    "name:zho_x_preferred":[
        "\u99ac\u91d1\u7fa4\u5cf6"
    ],
    "qs:name":"Kiebu Village",
    "qs:photos_9r":0,
    "qs:photos_sr":0,
    "qs:pop_sr":"2",
    "wd:wordcount":1392,
    "wof:name":"Kiebu Village",
    "wof:placetype":"locality",
    "wof:population":551
},
  "geometry": {"coordinates":[172.97461999999999,3.32342],"type":"Point"}
}