{
  "type": "Feature",
  "properties": {
    "gn:country":"KI",
    "gn:fcode":"PPL",
    "gn:pop":551,
    "iso:country":"KI",
    "qs:name":"Kiebu Village",
    "qs:photos_9r":0,
    "qs:photos_sr":0,
    "qs:pop_sr":"2",
    "wd:wordcount":1392,
    "wof:name":"Kiebu Village",
    "wof:placetype":"locality",
    "wof:population":551
},
  "geometry": {"coordinates":[172.97461999999999,3.32342],"type":"Point"}
}