{
  "type": "Feature",
  "properties": {
    "gn:country":"KI",
    "gn:fcode":"PPL",
    "gn:population":119,
    "iso:country":"KI",
    "name:ceb_x_preferred":[
        "Tabontebike Village"
    ],
    "name:eng_x_preferred":[
        "Tabontebike"
    ],
    "name:nld_x_preferred":[
        "Tabontebike"
    ],
    "name:pol_x_preferred":[
        "Tabontebike"
    ],
    "name:swe_x_preferred":[
        "Tabontebike Village"
    ],
    "qs:name":"Tabontebike Village",
    "qs:photos_9r":0,
    "qs:photos_sr":0,
    "qs:pop_sr":"1",
    "wd:wordcount":211,
    "wof:name":"Tabontebike Village",
    "wof:placetype":"locality",
    "wof:population":119
},
  "geometry": {"coordinates":[173.41144,0.23056],"type":"Point"}
}