{
  "type": "Feature",
  "properties": {
    "gn:country":"KI",
    "gn:fcode":"PPL",
    "gn:population":75,
    "iso:country":"KI",
    "name:eng_x_preferred":[
        "Tebikerei"
    ],
    "name:nld_x_preferred":[
        "Tebikerei"
    ],
    "name:und_x_variant":[
        "Bikerei"
    ],
    "qs:name":"Tebikerai Village",
    "qs:photos_9r":0,
    "qs:photos_sr":0,
    "qs:pop_sr":"1",
    "wd:wordcount":702,
    "wof:name":"Tebikerai Village",
    "wof:placetype":"locality",
    "wof:population":75
},
  "geometry": {"coordinates":[173.00391999999999,1.00789],"type":"Point"}
}