{
  "type": "Feature",
  "properties": {
    "gn:country":"KI",
    "gn:fcode":"PPL",
    "gn:pop":74,
    "iso:country":"KI",
    "name:dut_x_preferred":[
        "Teteirio"
    ],
    "name:eng_x_preferred":[
        "Teteirio"
    ],
    "qs:name":"Teteirio Village",
    "qs:photos_9r":0,
    "qs:photos_sr":0,
    "qs:pop_sr":"1",
    "wof:name":"Teteirio Village",
    "wof:placetype":"locality",
    "wof:population":74
},
  "geometry": {"coordinates":[175.99925999999999,-1.34313],"type":"Point"}
}