{
  "type": "Feature",
  "properties": {
    "gn:country":"KI",
    "gn:fcode":"LCTY",
    "gn:pop":12509,
    "iso:country":"KI",
    "qs:name":"Betio Town",
    "qs:photos_9r":0,
    "qs:photos_sr":0,
    "qs:pop_sr":"6",
    "wof:name":"Betio Town",
    "wof:placetype":"locality",
    "wof:population":12509
},
  "geometry": {"coordinates":[172.93360000000001,1.35046],"type":"Point"}
}