{
  "type": "Feature",
  "properties": {
    "gn:country":"KI",
    "gn:fcode":"PPL",
    "gn:pop":191,
    "iso:country":"KI",
    "name:eng_x_preferred":[
        "Abatiku"
    ],
    "name:fra_x_preferred":[
        "Abatiku"
    ],
    "name:swe_x_preferred":[
        "Abatiku Village"
    ],
    "qs:name":"Abatiku Village",
    "qs:photos_9r":0,
    "qs:photos_sr":0,
    "qs:pop_sr":"1",
    "wd:wordcount":1137,
    "wof:name":"Abatiku Village",
    "wof:placetype":"locality",
    "wof:population":191
},
  "geometry": {"coordinates":[173.77700999999999,0.38843],"type":"Point"}
}